{
   "sliders" : [
        {
          "id": 1,
          "title": "Gözəl Persiya Pişikləri",
          "url": "https://avatars.mds.yandex.net/i?id=686d0e849aeea67aeb3eb675e920eccc9d032cf9-12752503-images-thumbs&n=13"
        },
        {
          "id": 2,
          "title": "Hindistancevizi ilə Möhtəşəm Çimərliklər",
          "url": "https://avatars.mds.yandex.net/i?id=cdd2657b600997a5e234b720550ec8df66b4cda6-10638774-images-thumbs&n=13"
        },
        {
          "id": 3,
          "title": "İtaliyada Unikal Şəhər Mənzərələri",
          "url": "https://avatars.mds.yandex.net/i?id=b315f1354fa1c9662ab8248cb52ec5d40c1c351a-5315965-images-thumbs&n=13"
        },
        {
          "id": 4,
          "title": "Parlaq Aurora Borealis Səhnələri",
          "url": "https://avatars.mds.yandex.net/i?id=ba039a664c246f3e8c0dbb887ff37c9c990f08fa-3610079-images-thumbs&n=13"
        },
        {
          "id": 5,
          "title": "Tropik Meşə Üzərində Gün Doğumu",
          "url": "https://i.pinimg.com/originals/5d/39/52/5d39523f1be9264b36f4fed2c1509f3c.jpg"
        },
        {
          "id": 6,
          "title": "Klassik Avtomobil Şöhrəti",
          "url": "https://avatars.mds.yandex.net/i?id=04a605afc6503141a2072c4ae5816a706b59886f-8497900-images-thumbs&n=13"
        },
        {
          "id": 7,
          "title": "Rahatlıq üçün Minimalist Dizayn",
          "url": "https://avatars.mds.yandex.net/i?id=ba6e546aae224c84ebf9a8331a3c0455194f773a-4233036-images-thumbs&n=13"
        }
      ],
   "animals" : [
        {
          "id": 1,
          "name": "Simba",
          "animalType": "Pişik",
          "breed": "Persiya",
          "age": 2,
          "weight": "4 kg",
          "owner": "John Doe",
          "imageURL": "https://example.com/images/simba.jpg"
        },
        {
          "id": 2,
          "name": "Bella",
          "animalType": "İt",
          "breed": "Golden Retriever",
          "age": 3,
          "weight": "25 kg",
          "owner": "Jane Smith",
          "imageURL": "https://example.com/images/bella.jpg"
        },
        {
          "id": 3,
          "name": "Coco",
          "animalType": "Quş",
          "breed": "Tutuquşu",
          "age": 1,
          "weight": "0.2 kg",
          "owner": "Emily Davis",
          "imageURL": "https://example.com/images/coco.jpg"
        },
        {
          "id": 4,
          "name": "Luna",
          "animalType": "Pişik",
          "breed": "Bengal",
          "age": 4,
          "weight": "4.5 kg",
          "owner": "Michael Johnson",
          "imageURL": "https://example.com/images/luna.jpg"
        },
        {
          "id": 5,
          "name": "Max",
          "animalType": "İt",
          "breed": "Alman Çoban",
          "age": 5,
          "weight": "30 kg",
          "owner": "Chris Brown",
          "imageURL": "https://example.com/images/max.jpg"
        },
        {
          "id": 6,
          "name": "Charlie",
          "animalType": "Dovşan",
          "breed": "Angora",
          "age": 2,
          "weight": "3 kg",
          "owner": "Sophia Wilson",
          "imageURL": "https://example.com/images/charlie.jpg"
        },
        {
          "id": 7,
          "name": "Buddy",
          "animalType": "İt",
          "breed": "Beagle",
          "age": 3,
          "weight": "10 kg",
          "owner": "Daniel Lee",
          "imageURL": "https://example.com/images/buddy.jpg"
        },
        {
          "id": 8,
          "name": "Milo",
          "animalType": "Pişik",
          "breed": "Siam",
          "age": 1,
          "weight": "3.8 kg",
          "owner": "Olivia Martinez",
          "imageURL": "https://example.com/images/milo.jpg"
        }
      ]
      
}